tts_evaluate_yue/.gitattributes
tts_evaluate_yue/__init__.py
tts_evaluate_yue/py.typed
tts_evaluate_yue/asr/__init__.py
tts_evaluate_yue/asr/faster_whisper.py
tts_evaluate_yue/asr/huggingface.py
tts_evaluate_yue/cer/.gitattributes
tts_evaluate_yue/cer/README.md
tts_evaluate_yue/cer/app.py
tts_evaluate_yue/cer/cer.py
tts_evaluate_yue/cer/requirements.txt
tts_evaluate_yue/cer/test_cer.py
tts_evaluate_yue/cer/.cache/huggingface/.gitignore
tts_evaluate_yue/cer/.cache/huggingface/download/.gitattributes.lock
tts_evaluate_yue/cer/.cache/huggingface/download/.gitattributes.metadata
tts_evaluate_yue/cer/.cache/huggingface/download/README.md.lock
tts_evaluate_yue/cer/.cache/huggingface/download/README.md.metadata
tts_evaluate_yue/cer/.cache/huggingface/download/app.py.lock
tts_evaluate_yue/cer/.cache/huggingface/download/app.py.metadata
tts_evaluate_yue/cer/.cache/huggingface/download/cer.py.lock
tts_evaluate_yue/cer/.cache/huggingface/download/cer.py.metadata
tts_evaluate_yue/cer/.cache/huggingface/download/requirements.txt.lock
tts_evaluate_yue/cer/.cache/huggingface/download/requirements.txt.metadata
tts_evaluate_yue/cer/.cache/huggingface/download/test_cer.py.lock
tts_evaluate_yue/cer/.cache/huggingface/download/test_cer.py.metadata
tts_evaluate_yue/tts/__init__.py
tts_evaluate_yue/tts/cosyvoice.py
tts_evaluate_yue/tts/gtts.py
tts_evaluate_yue-2.2.0.dist-info/METADATA
tts_evaluate_yue-2.2.0.dist-info/WHEEL
tts_evaluate_yue-2.2.0.dist-info/RECORD
